sicfw/__init__.py
sicfw/sicfw.py
sicfw-0.0.3.dist-info/METADATA
sicfw-0.0.3.dist-info/WHEEL
sicfw-0.0.3.dist-info/top_level.txt
sicfw-0.0.3.dist-info/RECORD
