Metadata-Version: 2.1
Name: sicfw
Version: 0.0.3
Summary: Framework for simple interactive console.
Home-page: https://gitlab.com/kegeppa
Author: kegeppa
Author-email: 
Maintainer: kegeppa
Maintainer-email: 
License: MIT
Platform: UNKNOWN
Classifier: Programming Language :: Python :: 3
